ZetcodePhpJiaochengChuyiFix1/README.md
ZetcodePhpJiaochengChuyiFix1/__init__.py
ZetcodePhpJiaochengChuyiFix1/__main__.py
ZetcodePhpJiaochengChuyiFix1/file.epub
ZetcodePhpJiaochengChuyiFix1/index.html
ZetcodePhpJiaochengChuyiFix1/css/__init__.py
ZetcodePhpJiaochengChuyiFix1/css/annotations.css
ZetcodePhpJiaochengChuyiFix1/css/main.css
ZetcodePhpJiaochengChuyiFix1/css/normalize.css
ZetcodePhpJiaochengChuyiFix1/css/popup.css
ZetcodePhpJiaochengChuyiFix1/font/__init__.py
ZetcodePhpJiaochengChuyiFix1/font/fontello.eot
ZetcodePhpJiaochengChuyiFix1/font/fontello.svg
ZetcodePhpJiaochengChuyiFix1/font/fontello.ttf
ZetcodePhpJiaochengChuyiFix1/font/fontello.woff
ZetcodePhpJiaochengChuyiFix1/img/__init__.py
ZetcodePhpJiaochengChuyiFix1/img/annotator-glyph-sprite.png
ZetcodePhpJiaochengChuyiFix1/img/annotator-icon-sprite.png
ZetcodePhpJiaochengChuyiFix1/img/apple-touch-icon.png
ZetcodePhpJiaochengChuyiFix1/img/cancelfullscreen.png
ZetcodePhpJiaochengChuyiFix1/img/close.png
ZetcodePhpJiaochengChuyiFix1/img/fullscreen.png
ZetcodePhpJiaochengChuyiFix1/img/loader.gif
ZetcodePhpJiaochengChuyiFix1/img/menu-icon.png
ZetcodePhpJiaochengChuyiFix1/img/save.png
ZetcodePhpJiaochengChuyiFix1/img/saved.png
ZetcodePhpJiaochengChuyiFix1/img/settings-s.png
ZetcodePhpJiaochengChuyiFix1/img/settings.png
ZetcodePhpJiaochengChuyiFix1/img/star.png
ZetcodePhpJiaochengChuyiFix1/js/__init__.py
ZetcodePhpJiaochengChuyiFix1/js/epub.js
ZetcodePhpJiaochengChuyiFix1/js/epub.min.js
ZetcodePhpJiaochengChuyiFix1/js/epub.min.map
ZetcodePhpJiaochengChuyiFix1/js/hooks.min.js
ZetcodePhpJiaochengChuyiFix1/js/hooks.min.map
ZetcodePhpJiaochengChuyiFix1/js/reader.js
ZetcodePhpJiaochengChuyiFix1/js/reader.js.map
ZetcodePhpJiaochengChuyiFix1/js/reader.min.js
ZetcodePhpJiaochengChuyiFix1/js/reader.min.map
ZetcodePhpJiaochengChuyiFix1/js/hooks/__init__.py
ZetcodePhpJiaochengChuyiFix1/js/hooks/extensions/__init__.py
ZetcodePhpJiaochengChuyiFix1/js/hooks/extensions/highlight.js
zetcode_php_jiaocheng_chuyi_fix1-2025.3.24.0.dist-info/METADATA
zetcode_php_jiaocheng_chuyi_fix1-2025.3.24.0.dist-info/WHEEL
zetcode_php_jiaocheng_chuyi_fix1-2025.3.24.0.dist-info/entry_points.txt
zetcode_php_jiaocheng_chuyi_fix1-2025.3.24.0.dist-info/top_level.txt
zetcode_php_jiaocheng_chuyi_fix1-2025.3.24.0.dist-info/RECORD
